akdogan/__init__.py
akdogan/__main__.py
akdogan/file_utils.py
akdogan/snapshot.py
akdogan/tree_utils.py
akdogan-1.1.0.dist-info/licenses/LICENSE
akdogan-1.1.0.dist-info/METADATA
akdogan-1.1.0.dist-info/WHEEL
akdogan-1.1.0.dist-info/entry_points.txt
akdogan-1.1.0.dist-info/top_level.txt
akdogan-1.1.0.dist-info/RECORD
