Metadata-Version: 2.4
Name: akdogan
Version: 1.1.0
Summary: Universal LLM-optimized project snapshot tool
Author: Berke Akdogan
License: MIT License
Keywords: llm,snapshot,ai,code-extractor,project-tree
Requires-Python: >=3.8
License-File: LICENSE
Requires-Dist: pandas
Requires-Dist: openpyxl
Dynamic: license-file
